Spire.Presentation.Free-9.12.0.dist-info/METADATA
Spire.Presentation.Free-9.12.0.dist-info/RECORD
Spire.Presentation.Free-9.12.0.dist-info/WHEEL
Spire.Presentation.Free-9.12.0.dist-info/top_level.txt
spire/__init__.py
spire/presentation/ActiveSlide.py
spire/presentation/AnimateType.py
spire/presentation/AnimationCalculationMode.py
spire/presentation/AnimationColorBehavior.py
spire/presentation/AnimationColorDirection.py
spire/presentation/AnimationColorTransform.py
spire/presentation/AnimationColorspace.py
spire/presentation/AnimationCommandBehavior.py
spire/presentation/AnimationCommandType.py
spire/presentation/AnimationEffect.py
spire/presentation/AnimationEffectCollection.py
spire/presentation/AnimationEffectSubtype.py
spire/presentation/AnimationEffectType.py
spire/presentation/AnimationFilterEffect.py
spire/presentation/AnimationMotion.py
spire/presentation/AnimationMotionOrigin.py
spire/presentation/AnimationMotionPathEditMode.py
spire/presentation/AnimationProperty.py
spire/presentation/AnimationRepeatType.py
spire/presentation/AnimationRestartType.py
spire/presentation/AnimationRotation.py
spire/presentation/AnimationScale.py
spire/presentation/AnimationSet.py
spire/presentation/AnimationTriggerType.py
spire/presentation/AppException.py
spire/presentation/AudioCD.py
spire/presentation/AudioPlayMode.py
spire/presentation/AudioVolumeType.py
spire/presentation/AxisPositionType.py
spire/presentation/AxisType.py
spire/presentation/Backdrop.py
spire/presentation/BackgroundType.py
spire/presentation/BaseShapeLocking.py
spire/presentation/BehaviorAccumulateType.py
spire/presentation/BehaviorAdditiveType.py
spire/presentation/BevelColorType.py
spire/presentation/BevelPresetType.py
spire/presentation/BlackWhiteMode.py
spire/presentation/BlendEffect.py
spire/presentation/BlendMode.py
spire/presentation/BlindsSlideTransition.py
spire/presentation/BlurNode.py
spire/presentation/Camera.py
spire/presentation/Cell.py
spire/presentation/CellCollection.py
spire/presentation/CellRange.py
spire/presentation/CellRanges.py
spire/presentation/ChartAxis.py
spire/presentation/ChartBaseUnitType.py
